{"cameraMode":{"drawMode":0,"name":"Shaded","section":"Shading Mode"},"sceneLighting":true,"audioPlay":false,"sceneViewState":{"showFog":true,"showMaterialUpdate":false,"showSkybox":true,"showFlares":true,"showImageEffects":true,"showParticleSystems":true,"showVisualEffectGraphs":true,"m_FxEnabled":true},"in2DMode":false,"pivot":{"x":491.1484069824219,"y":-85.12496185302735,"z":757.6631469726563},"rotation":{"x":0.13029485940933228,"y":-0.6976582407951355,"z":0.15744803845882417,"w":0.6888532042503357},"size":156.99874877929688,"orthographic":false}